django_model_settings-0.3.1.dist-info/DESCRIPTION.rst
django_model_settings-0.3.1.dist-info/METADATA
django_model_settings-0.3.1.dist-info/RECORD
django_model_settings-0.3.1.dist-info/WHEEL
django_model_settings-0.3.1.dist-info/metadata.json
django_model_settings-0.3.1.dist-info/top_level.txt
model_settings/__init__.py
model_settings/__init__.pyc
model_settings/admin.py
model_settings/apps.py
model_settings/context_processors.py
model_settings/models.py
model_settings/utils.py
model_settings/utils.pyc
model_settings/migrations/0001_initial.py
model_settings/migrations/0002_auto_20150810_1620.py
model_settings/migrations/__init__.py
model_settings/south_migrations/0001_initial.py
model_settings/south_migrations/0002_auto__add_image.py
model_settings/south_migrations/__init__.py
model_settings/templatetags/__init__.py
model_settings/templatetags/model_settings_tags.py
model_settings/tests/coverage.conf
model_settings/tests/runtests.py
model_settings/tests/tests.py
