Metadata-Version: 2.0
Name: django-model-settings
Version: 0.3.1
Summary: Editable settings via polymorphic models with a dict-like interface and template tags.
Home-page: https://github.com/ixc/django-model-settings
Author: Interaction Consortium
Author-email: studio@interaction.net.au
License: MIT
Platform: UNKNOWN
Requires-Dist: django-classy-tags
Requires-Dist: django-polymorphic
Provides-Extra: test
Requires-Dist: coverage (==4.2); extra == 'test'
